kale/__init__.py
kale/consumer.py
kale/crypt.py
kale/default_settings.py
kale/exceptions.py
kale/message.py
kale/publisher.py
kale/queue_info.py
kale/queue_selector.py
kale/sqs.py
kale/task.py
kale/test_utils.py
kale/timeout.py
kale/utils.py
kale/version.py
kale/worker.py
wrk-0.3.1.dist-info/LICENSE.txt
wrk-0.3.1.dist-info/METADATA
wrk-0.3.1.dist-info/WHEEL
wrk-0.3.1.dist-info/top_level.txt
wrk-0.3.1.dist-info/RECORD
