Metadata-Version: 2.1
Name: wrk
Version: 0.3.1
Summary: Kale: A Task Worker Library from Nextdoor Clone
Home-page: https://github.com/caputomarcos/ndkale
Author: Marcos Caputo
Author-email: caputo.marcos@gmail.com.com
License: Apache License, Version 2
Download-URL: http://pypi.python.org/pypi/ndkale#downloads
Keywords: kale nextdoor taskworker sqs python
Platform: UNKNOWN
Classifier: Development Status :: 5 - Production/Stable
Classifier: License :: OSI Approved :: BSD License
Classifier: Topic :: System :: Distributed Computing
Classifier: Topic :: Software Development :: Object Brokering
Classifier: Programming Language :: Python
Classifier: Programming Language :: Python
Classifier: Programming Language :: Python :: 2.7
Classifier: Programming Language :: Python :: 3.5
Classifier: Programming Language :: Python :: 3.6
Classifier: Programming Language :: Python :: 3.7
Classifier: Programming Language :: Python :: Implementation :: CPython
Classifier: Operating System :: OS Independent
Requires-Dist: boto
Requires-Dist: future
Requires-Dist: pycryptodome
Requires-Dist: pyyaml
Requires-Dist: setuptools
Requires-Dist: six
